<?xml version="1.0" encoding="UTF-8"?>
<metadata xml:lang="en"><Esri><CreaDate>20211222</CreaDate><CreaTime>17011700</CreaTime><ArcGISFormat>1.0</ArcGISFormat><SyncOnce>TRUE</SyncOnce><DataProperties><itemProps><itemLocation><linkage Sync="TRUE">file://\\DESKTOP-5CK68UJ\D$\work\NLCZ\experience\zone\TPLocalClimateRegionalization\LCZ\localClimateZone_1979_1988</linkage><protocol Sync="TRUE">Local Area Network</protocol></itemLocation></itemProps><copyHistory><copy source="D:\work\NLCZ\experience\zone\TPLocalClimateRegionalization\zone_1979_1988\localClimateZone_1979_1988" dest="\\DESKTOP-5CK68UJ\D$\work\NLCZ\experience\zone\TPLocalClimateRegionalization\LCZ\localClimateZone_1979_1988" date="20220907" time="16494300"></copy></copyHistory><lineage><Process ToolSource="c:\program files (x86)\arcgis\desktop10.2\ArcToolbox\Toolboxes\Data Management Tools.tbx\DefineProjection" Date="20220216" Time="144521">DefineProjection localClimateZone_1979_1988 PROJCS['WGS_1984_UTM_Zone_45N',GEOGCS['GCS_WGS_1984',DATUM['D_WGS_1984',SPHEROID['WGS_1984',6378137.0,298.257223563]],PRIMEM['Greenwich',0.0],UNIT['Degree',0.0174532925199433]],PROJECTION['Transverse_Mercator'],PARAMETER['false_easting',500000.0],PARAMETER['false_northing',0.0],PARAMETER['central_meridian',87.0],PARAMETER['scale_factor',0.9996],PARAMETER['latitude_of_origin',0.0],UNIT['Meter',1.0]]</Process><Process ToolSource="c:\program files (x86)\arcgis\desktop10.2\ArcToolbox\Toolboxes\Data Management Tools.tbx\CalculateField" Date="20220907" Time="143548">CalculateField ZONE\localClimateZone_1979_1988 LCZ_ID [FID] VB #</Process></lineage></DataProperties></Esri></metadata>
